{"metadata": {"dbt_schema_version": "https://schemas.getdbt.com/dbt/run-results/v6.json", "dbt_version": "1.11.12", "generated_at": "2026-07-13T14:22:03.260351Z", "invocation_id": "e9f5537f-9d67-40f4-928c-6beecbee3814", "invocation_started_at": "2026-07-13T14:21:58.059715Z", "env": {}}, "results": [{"status": "success", "timing": [{"name": "compile", "started_at": "2026-07-13T14:22:02.730762Z", "completed_at": "2026-07-13T14:22:02.749512Z"}, {"name": "execute", "started_at": "2026-07-13T14:22:02.752140Z", "completed_at": "2026-07-13T14:22:02.752162Z"}], "thread_id": "Thread-3 (worker)", "execution_time": 0.036499738693237305, "adapter_response": {}, "message": null, "failures": null, "unique_id": "model.rebate_transformation_layer.stg_partners", "compiled": true, "compiled_code": "with source_data as (\n    select * from DEV_MCP_DB.PUBLIC.synthetic_dim_partner\n)\n\nselect\n    cast(partner_id as varchar) as partner_id,\n    cast(partner_name as varchar) as partner_name,\n    cast(partner_type as varchar) as partner_type\nfrom source_data", "relation_name": "DEV_MCP_DB.PUBLIC.stg_partners", "batch_results": null}, {"status": "success", "timing": [{"name": "compile", "started_at": "2026-07-13T14:22:02.738479Z", "completed_at": "2026-07-13T14:22:02.750252Z"}, {"name": "execute", "started_at": "2026-07-13T14:22:02.753369Z", "completed_at": "2026-07-13T14:22:02.753380Z"}], "thread_id": "Thread-5 (worker)", "execution_time": 0.03521132469177246, "adapter_response": {}, "message": null, "failures": null, "unique_id": "test.rebate_transformation_layer.source_not_null_bronze_source_synthetic_dim_affiliate_affiliate_id.4b0278fffa", "compiled": true, "compiled_code": "\n    \n    \n\n\n\nselect affiliate_id\nfrom DEV_MCP_DB.PUBLIC.synthetic_dim_affiliate\nwhere affiliate_id is null\n\n\n", "relation_name": null, "batch_results": null}, {"status": "success", "timing": [{"name": "compile", "started_at": "2026-07-13T14:22:02.719660Z", "completed_at": "2026-07-13T14:22:02.750872Z"}, {"name": "execute", "started_at": "2026-07-13T14:22:02.754399Z", "completed_at": "2026-07-13T14:22:02.754412Z"}], "thread_id": "Thread-2 (worker)", "execution_time": 0.0410456657409668, "adapter_response": {}, "message": null, "failures": null, "unique_id": "model.rebate_transformation_layer.stg_affiliates", "compiled": true, "compiled_code": "with source_data as (\n    select * from DEV_MCP_DB.PUBLIC.synthetic_dim_affiliate\n)\n\nselect \n    cast(affiliate_id as varchar) as affiliate_id,\n    cast(affiliate_name as varchar) as affiliate_name,\n    cast(parent_id as varchar) as parent_id,\n    cast(state as varchar) as state,\n    cast(program_tier as varchar) as program_tier\nfrom source_data", "relation_name": "DEV_MCP_DB.PUBLIC.stg_affiliates", "batch_results": null}, {"status": "success", "timing": [{"name": "compile", "started_at": "2026-07-13T14:22:02.734762Z", "completed_at": "2026-07-13T14:22:02.751540Z"}, {"name": "execute", "started_at": "2026-07-13T14:22:02.755415Z", "completed_at": "2026-07-13T14:22:02.755426Z"}], "thread_id": "Thread-4 (worker)", "execution_time": 0.03797650337219238, "adapter_response": {}, "message": null, "failures": null, "unique_id": "model.rebate_transformation_layer.stg_transactions", "compiled": true, "compiled_code": "with source_data as (\n    select * from DEV_MCP_DB.PUBLIC.synthetic_fact_rebate\n)\n\nselect \n    cast(transaction_id as varchar) as transaction_id,\n    cast(affiliate_id as varchar) as affiliate_id,\n    cast(partner_id as varchar) as partner_id,\n    cast(transaction_date as date) as transaction_date,\n    cast(memo as varchar) as memo,\n    cast(net_amount as decimal(18, 2)) as net_amount\nfrom source_data", "relation_name": "DEV_MCP_DB.PUBLIC.stg_transactions", "batch_results": null}, {"status": "success", "timing": [{"name": "compile", "started_at": "2026-07-13T14:22:02.764087Z", "completed_at": "2026-07-13T14:22:02.786182Z"}, {"name": "execute", "started_at": "2026-07-13T14:22:02.787467Z", "completed_at": "2026-07-13T14:22:02.787485Z"}], "thread_id": "Thread-3 (worker)", "execution_time": 0.02831268310546875, "adapter_response": {}, "message": null, "failures": null, "unique_id": "test.rebate_transformation_layer.source_not_null_bronze_source_synthetic_dim_partner_partner_id.75e112addf", "compiled": true, "compiled_code": "\n    \n    \n\n\n\nselect partner_id\nfrom DEV_MCP_DB.PUBLIC.synthetic_dim_partner\nwhere partner_id is null\n\n\n", "relation_name": null, "batch_results": null}, {"status": "success", "timing": [{"name": "compile", "started_at": "2026-07-13T14:22:02.769243Z", "completed_at": "2026-07-13T14:22:02.786823Z"}, {"name": "execute", "started_at": "2026-07-13T14:22:02.789530Z", "completed_at": "2026-07-13T14:22:02.789544Z"}], "thread_id": "Thread-5 (worker)", "execution_time": 0.029730796813964844, "adapter_response": {}, "message": null, "failures": null, "unique_id": "test.rebate_transformation_layer.source_not_null_bronze_source_synthetic_fact_rebate_transaction_id.75de2e1126", "compiled": true, "compiled_code": "\n    \n    \n\n\n\nselect transaction_id\nfrom DEV_MCP_DB.PUBLIC.synthetic_fact_rebate\nwhere transaction_id is null\n\n\n", "relation_name": null, "batch_results": null}, {"status": "success", "timing": [{"name": "compile", "started_at": "2026-07-13T14:22:02.776636Z", "completed_at": "2026-07-13T14:22:02.788369Z"}, {"name": "execute", "started_at": "2026-07-13T14:22:02.791096Z", "completed_at": "2026-07-13T14:22:02.791110Z"}], "thread_id": "Thread-2 (worker)", "execution_time": 0.030612707138061523, "adapter_response": {}, "message": null, "failures": null, "unique_id": "model.rebate_transformation_layer.int_partners", "compiled": true, "compiled_code": "with staging_partners as (\n    select * from DEV_MCP_DB.PUBLIC.stg_partners\n)\n\nselect\n    partner_id,\n    upper(trim(partner_name)) as partner_name,\n    upper(trim(partner_type)) as partner_type\nfrom staging_partners", "relation_name": "DEV_MCP_DB.PUBLIC.int_partners", "batch_results": null}, {"status": "success", "timing": [{"name": "compile", "started_at": "2026-07-13T14:22:02.780228Z", "completed_at": "2026-07-13T14:22:02.788940Z"}, {"name": "execute", "started_at": "2026-07-13T14:22:02.791956Z", "completed_at": "2026-07-13T14:22:02.791966Z"}], "thread_id": "Thread-4 (worker)", "execution_time": 0.030838489532470703, "adapter_response": {}, "message": null, "failures": null, "unique_id": "test.rebate_transformation_layer.not_null_stg_partners_partner_id.dd03ad0f34", "compiled": true, "compiled_code": "\n    \n    \n\n\n\nselect partner_id\nfrom DEV_MCP_DB.PUBLIC.stg_partners\nwhere partner_id is null\n\n\n", "relation_name": null, "batch_results": null}, {"status": "success", "timing": [{"name": "compile", "started_at": "2026-07-13T14:22:02.798691Z", "completed_at": "2026-07-13T14:22:02.822076Z"}, {"name": "execute", "started_at": "2026-07-13T14:22:02.823548Z", "completed_at": "2026-07-13T14:22:02.823572Z"}], "thread_id": "Thread-3 (worker)", "execution_time": 0.03018784523010254, "adapter_response": {}, "message": null, "failures": null, "unique_id": "test.rebate_transformation_layer.unique_stg_partners_partner_id.24703096a2", "compiled": true, "compiled_code": "\n    \n    \n\nselect\n    partner_id as unique_field,\n    count(*) as n_records\n\nfrom DEV_MCP_DB.PUBLIC.stg_partners\nwhere partner_id is not null\ngroup by partner_id\nhaving count(*) > 1\n\n\n", "relation_name": null, "batch_results": null}, {"status": "success", "timing": [{"name": "compile", "started_at": "2026-07-13T14:22:02.807620Z", "completed_at": "2026-07-13T14:22:02.822676Z"}, {"name": "execute", "started_at": "2026-07-13T14:22:02.825007Z", "completed_at": "2026-07-13T14:22:02.825018Z"}], "thread_id": "Thread-5 (worker)", "execution_time": 0.02946758270263672, "adapter_response": {}, "message": null, "failures": null, "unique_id": "model.rebate_transformation_layer.int_affiliates", "compiled": true, "compiled_code": "with staging_affiliates as (\n    select * from DEV_MCP_DB.PUBLIC.stg_affiliates\n)\n\nselect\n    affiliate_id,\n    upper(trim(affiliate_name)) as affiliate_name,\n    parent_id,\n    upper(trim(state)) as state,\n    upper(trim(program_tier)) as program_tier\nfrom staging_affiliates", "relation_name": "DEV_MCP_DB.PUBLIC.int_affiliates", "batch_results": null}, {"status": "success", "timing": [{"name": "compile", "started_at": "2026-07-13T14:22:02.811360Z", "completed_at": "2026-07-13T14:22:02.824377Z"}, {"name": "execute", "started_at": "2026-07-13T14:22:02.826644Z", "completed_at": "2026-07-13T14:22:02.826657Z"}], "thread_id": "Thread-2 (worker)", "execution_time": 0.02992105484008789, "adapter_response": {}, "message": null, "failures": null, "unique_id": "model.rebate_transformation_layer.int_rebates", "compiled": true, "compiled_code": "-- Intermediate Layer: Rebate table Deduplication and Anaomaly Detection\n-- This model performs row-level deduplication of rebate transactions\n-- and flags anomalies to be interpreted by the gold/marts layer \n-- Current anomalies tracked:  \n-- - null_amount: Transacted amount is missing or null \n-- - negative_amount: Transacted amount falls below $0.00 \n-- - zero_amount: Transacted amount is exactly $0.00 \n-- - null_memo: Transaction is missing descriptive tracking notes \n-- - null_partner: Transaction is missing the partner_id identifier \n-- Finally, this table uses a composite surrogate key to prevent tracking collisions and\n-- provides standardized calendar dimensions (year/month) for downstream analysis.\n\n\nwith staging_transactions as (\n    select * from DEV_MCP_DB.PUBLIC.stg_transactions\n),\n\ndeduplicated as (\n    select\n        transaction_id,\n        affiliate_id,\n        partner_id,\n        -- Date standardization\n        cast(transaction_date as date) as transaction_date,\n        extract(year from cast(transaction_date as date)) as transaction_year,\n        extract(month from cast(transaction_date as date)) as transaction_month,\n        memo,\n        net_amount,\n        md5(cast(coalesce(cast(transaction_id as varchar), '') || '-' ||\n                 coalesce(cast(partner_id as varchar), '') || '-' ||\n                 coalesce(cast(memo as varchar), '') as varchar)) as unique_key,\n        row_number() over (\n            partition by transaction_id, partner_id, memo, net_amount\n            order by cast(transaction_date as date) desc\n        ) as row_num\n    from staging_transactions\n),\n\nflagged as (\n    select\n        unique_key,\n        transaction_id,\n        affiliate_id,\n        partner_id,\n        transaction_date,\n        transaction_year,\n        transaction_month,\n        memo,\n        net_amount,\n        -- Exception typing at the row level\n        -- Silver identifies WHAT is anomalous, Gold determines WHY\n        case\n            when net_amount is null then 'null_amount'\n            when net_amount < 0.00 then 'negative_amount'\n            when net_amount = 0.00 then 'zero_amount'\n            when memo is null then 'null_memo'\n            when partner_id is null then 'null_partner'\n            else null\n        end as exception_type,\n        case\n            when net_amount is null\n              or net_amount <= 0.00\n              or memo is null\n              or partner_id is null\n            then true\n            else false\n        end as is_exception\n    from deduplicated\n    where row_num = 1\n)\n\nselect * from flagged", "relation_name": "DEV_MCP_DB.PUBLIC.int_rebates", "batch_results": null}, {"status": "success", "timing": [{"name": "compile", "started_at": "2026-07-13T14:22:02.816233Z", "completed_at": "2026-07-13T14:22:02.827662Z"}, {"name": "execute", "started_at": "2026-07-13T14:22:02.830506Z", "completed_at": "2026-07-13T14:22:02.830518Z"}], "thread_id": "Thread-4 (worker)", "execution_time": 0.033119916915893555, "adapter_response": {}, "message": null, "failures": null, "unique_id": "test.rebate_transformation_layer.dbt_utils_unique_combination_of_columns_stg_transactions_transaction_id__partner_id__memo.b655c5c05c", "compiled": true, "compiled_code": "\n\n\n\n\n\nwith validation_errors as (\n\n    select\n        transaction_id, partner_id, memo\n    from DEV_MCP_DB.PUBLIC.stg_transactions\n    group by transaction_id, partner_id, memo\n    having count(*) > 1\n\n)\n\nselect *\nfrom validation_errors\n\n\n", "relation_name": null, "batch_results": null}, {"status": "success", "timing": [{"name": "compile", "started_at": "2026-07-13T14:22:02.834529Z", "completed_at": "2026-07-13T14:22:02.852970Z"}, {"name": "execute", "started_at": "2026-07-13T14:22:02.861812Z", "completed_at": "2026-07-13T14:22:02.861838Z"}], "thread_id": "Thread-3 (worker)", "execution_time": 0.03310060501098633, "adapter_response": {}, "message": null, "failures": null, "unique_id": "test.rebate_transformation_layer.not_null_stg_affiliates_affiliate_id.cd62ea8f9d", "compiled": true, "compiled_code": "\n    \n    \n\n\n\nselect affiliate_id\nfrom DEV_MCP_DB.PUBLIC.stg_affiliates\nwhere affiliate_id is null\n\n\n", "relation_name": null, "batch_results": null}, {"status": "success", "timing": [{"name": "compile", "started_at": "2026-07-13T14:22:02.841430Z", "completed_at": "2026-07-13T14:22:02.853719Z"}, {"name": "execute", "started_at": "2026-07-13T14:22:02.863327Z", "completed_at": "2026-07-13T14:22:02.863339Z"}], "thread_id": "Thread-5 (worker)", "execution_time": 0.032053470611572266, "adapter_response": {}, "message": null, "failures": null, "unique_id": "test.rebate_transformation_layer.not_null_stg_transactions_affiliate_id.fca7c71d83", "compiled": true, "compiled_code": "\n    \n    \n\n\n\nselect affiliate_id\nfrom DEV_MCP_DB.PUBLIC.stg_transactions\nwhere affiliate_id is null\n\n\n", "relation_name": null, "batch_results": null}, {"status": "success", "timing": [{"name": "compile", "started_at": "2026-07-13T14:22:02.846724Z", "completed_at": "2026-07-13T14:22:02.862705Z"}, {"name": "execute", "started_at": "2026-07-13T14:22:02.864967Z", "completed_at": "2026-07-13T14:22:02.864980Z"}], "thread_id": "Thread-2 (worker)", "execution_time": 0.03252863883972168, "adapter_response": {}, "message": null, "failures": null, "unique_id": "test.rebate_transformation_layer.not_null_stg_transactions_transaction_id.1d00a8e2e4", "compiled": true, "compiled_code": "\n    \n    \n\n\n\nselect transaction_id\nfrom DEV_MCP_DB.PUBLIC.stg_transactions\nwhere transaction_id is null\n\n\n", "relation_name": null, "batch_results": null}, {"status": "success", "timing": [{"name": "compile", "started_at": "2026-07-13T14:22:02.854314Z", "completed_at": "2026-07-13T14:22:02.865794Z"}, {"name": "execute", "started_at": "2026-07-13T14:22:02.868411Z", "completed_at": "2026-07-13T14:22:02.868421Z"}], "thread_id": "Thread-4 (worker)", "execution_time": 0.027759552001953125, "adapter_response": {}, "message": null, "failures": null, "unique_id": "test.rebate_transformation_layer.relationships_stg_transactions_affiliate_id__affiliate_id__source_bronze_source_synthetic_dim_affiliate_.4ff8b17813", "compiled": true, "compiled_code": "\n    \n    \n\nwith child as (\n    select affiliate_id as from_field\n    from DEV_MCP_DB.PUBLIC.stg_transactions\n    where affiliate_id is not null\n),\n\nparent as (\n    select affiliate_id as to_field\n    from DEV_MCP_DB.PUBLIC.synthetic_dim_affiliate\n)\n\nselect\n    from_field\n\nfrom child\nleft join parent\n    on child.from_field = parent.to_field\n\nwhere parent.to_field is null\n\n\n", "relation_name": null, "batch_results": null}, {"status": "success", "timing": [{"name": "compile", "started_at": "2026-07-13T14:22:02.872333Z", "completed_at": "2026-07-13T14:22:02.890789Z"}, {"name": "execute", "started_at": "2026-07-13T14:22:02.896057Z", "completed_at": "2026-07-13T14:22:02.896074Z"}], "thread_id": "Thread-3 (worker)", "execution_time": 0.02909684181213379, "adapter_response": {}, "message": null, "failures": null, "unique_id": "test.rebate_transformation_layer.unique_stg_affiliates_affiliate_id.42d849c15c", "compiled": true, "compiled_code": "\n    \n    \n\nselect\n    affiliate_id as unique_field,\n    count(*) as n_records\n\nfrom DEV_MCP_DB.PUBLIC.stg_affiliates\nwhere affiliate_id is not null\ngroup by affiliate_id\nhaving count(*) > 1\n\n\n", "relation_name": null, "batch_results": null}, {"status": "success", "timing": [{"name": "compile", "started_at": "2026-07-13T14:22:02.884571Z", "completed_at": "2026-07-13T14:22:02.895399Z"}, {"name": "execute", "started_at": "2026-07-13T14:22:02.897744Z", "completed_at": "2026-07-13T14:22:02.897757Z"}], "thread_id": "Thread-2 (worker)", "execution_time": 0.027399063110351562, "adapter_response": {}, "message": null, "failures": null, "unique_id": "test.rebate_transformation_layer.unique_int_partners_partner_id.581c951ac5", "compiled": true, "compiled_code": "\n    \n    \n\nselect\n    partner_id as unique_field,\n    count(*) as n_records\n\nfrom DEV_MCP_DB.PUBLIC.int_partners\nwhere partner_id is not null\ngroup by partner_id\nhaving count(*) > 1\n\n\n", "relation_name": null, "batch_results": null}, {"status": "success", "timing": [{"name": "compile", "started_at": "2026-07-13T14:22:02.879008Z", "completed_at": "2026-07-13T14:22:02.897134Z"}, {"name": "execute", "started_at": "2026-07-13T14:22:02.899902Z", "completed_at": "2026-07-13T14:22:02.899914Z"}], "thread_id": "Thread-5 (worker)", "execution_time": 0.030716419219970703, "adapter_response": {}, "message": null, "failures": null, "unique_id": "test.rebate_transformation_layer.not_null_int_partners_partner_id.9c6409907f", "compiled": true, "compiled_code": "\n    \n    \n\n\n\nselect partner_id\nfrom DEV_MCP_DB.PUBLIC.int_partners\nwhere partner_id is null\n\n\n", "relation_name": null, "batch_results": null}, {"status": "success", "timing": [{"name": "compile", "started_at": "2026-07-13T14:22:02.891622Z", "completed_at": "2026-07-13T14:22:02.898630Z"}, {"name": "execute", "started_at": "2026-07-13T14:22:02.901465Z", "completed_at": "2026-07-13T14:22:02.901476Z"}], "thread_id": "Thread-4 (worker)", "execution_time": 0.023200035095214844, "adapter_response": {}, "message": null, "failures": null, "unique_id": "model.rebate_transformation_layer.dim_partners", "compiled": true, "compiled_code": "with affiliates as (\n    select * from DEV_MCP_DB.PUBLIC.int_affiliates\n),\n\npartners as (\n    select * from DEV_MCP_DB.PUBLIC.int_partners\n)\n\nselect\n    a.affiliate_id,\n    a.affiliate_name,\n    a.parent_id,\n    a.state,\n    a.program_tier,\n    p.partner_id,\n    p.partner_name,\n    p.partner_type\nfrom affiliates a\nleft join partners p on a.parent_id = p.partner_id", "relation_name": "DEV_MCP_DB.PUBLIC.dim_partners", "batch_results": null}, {"status": "success", "timing": [{"name": "compile", "started_at": "2026-07-13T14:22:02.907515Z", "completed_at": "2026-07-13T14:22:02.924723Z"}, {"name": "execute", "started_at": "2026-07-13T14:22:02.931305Z", "completed_at": "2026-07-13T14:22:02.931322Z"}], "thread_id": "Thread-3 (worker)", "execution_time": 0.029117345809936523, "adapter_response": {}, "message": null, "failures": null, "unique_id": "test.rebate_transformation_layer.not_null_int_affiliates_affiliate_id.10c7e1b3cd", "compiled": true, "compiled_code": "\n    \n    \n\n\n\nselect affiliate_id\nfrom DEV_MCP_DB.PUBLIC.int_affiliates\nwhere affiliate_id is null\n\n\n", "relation_name": null, "batch_results": null}, {"status": "success", "timing": [{"name": "compile", "started_at": "2026-07-13T14:22:02.913716Z", "completed_at": "2026-07-13T14:22:02.930675Z"}, {"name": "execute", "started_at": "2026-07-13T14:22:02.932954Z", "completed_at": "2026-07-13T14:22:02.932967Z"}], "thread_id": "Thread-2 (worker)", "execution_time": 0.02950143814086914, "adapter_response": {}, "message": null, "failures": null, "unique_id": "test.rebate_transformation_layer.unique_int_affiliates_affiliate_id.3072b935c8", "compiled": true, "compiled_code": "\n    \n    \n\nselect\n    affiliate_id as unique_field,\n    count(*) as n_records\n\nfrom DEV_MCP_DB.PUBLIC.int_affiliates\nwhere affiliate_id is not null\ngroup by affiliate_id\nhaving count(*) > 1\n\n\n", "relation_name": null, "batch_results": null}, {"status": "success", "timing": [{"name": "compile", "started_at": "2026-07-13T14:22:02.921047Z", "completed_at": "2026-07-13T14:22:02.932368Z"}, {"name": "execute", "started_at": "2026-07-13T14:22:02.935050Z", "completed_at": "2026-07-13T14:22:02.935060Z"}], "thread_id": "Thread-5 (worker)", "execution_time": 0.029494762420654297, "adapter_response": {}, "message": null, "failures": null, "unique_id": "model.rebate_transformation_layer.fact_rebate_payouts", "compiled": true, "compiled_code": "with rebates as (\n    select * from DEV_MCP_DB.PUBLIC.int_rebates\n)\n\nselect\n    unique_key as rebate_payout_id,\n    transaction_id,\n    affiliate_id,\n    partner_id,\n    transaction_date,\n    transaction_year,\n    transaction_month,\n    memo,\n    net_amount as rebate_amount\nfrom rebates\nwhere is_exception = false", "relation_name": "DEV_MCP_DB.PUBLIC.fact_rebate_payouts", "batch_results": null}, {"status": "success", "timing": [{"name": "compile", "started_at": "2026-07-13T14:22:02.925438Z", "completed_at": "2026-07-13T14:22:02.933822Z"}, {"name": "execute", "started_at": "2026-07-13T14:22:02.936578Z", "completed_at": "2026-07-13T14:22:02.936589Z"}], "thread_id": "Thread-4 (worker)", "execution_time": 0.02980494499206543, "adapter_response": {}, "message": null, "failures": null, "unique_id": "test.rebate_transformation_layer.not_null_int_rebates_unique_key.cda030b92a", "compiled": true, "compiled_code": "\n    \n    \n\n\n\nselect unique_key\nfrom DEV_MCP_DB.PUBLIC.int_rebates\nwhere unique_key is null\n\n\n", "relation_name": null, "batch_results": null}, {"status": "success", "timing": [{"name": "compile", "started_at": "2026-07-13T14:22:02.942907Z", "completed_at": "2026-07-13T14:22:02.965627Z"}, {"name": "execute", "started_at": "2026-07-13T14:22:02.966912Z", "completed_at": "2026-07-13T14:22:02.966935Z"}], "thread_id": "Thread-3 (worker)", "execution_time": 0.029581785202026367, "adapter_response": {}, "message": null, "failures": null, "unique_id": "test.rebate_transformation_layer.unique_int_rebates_unique_key.2eacea7120", "compiled": true, "compiled_code": "\n    \n    \n\nselect\n    unique_key as unique_field,\n    count(*) as n_records\n\nfrom DEV_MCP_DB.PUBLIC.int_rebates\nwhere unique_key is not null\ngroup by unique_key\nhaving count(*) > 1\n\n\n", "relation_name": null, "batch_results": null}, {"status": "success", "timing": [{"name": "compile", "started_at": "2026-07-13T14:22:02.948934Z", "completed_at": "2026-07-13T14:22:02.966277Z"}, {"name": "execute", "started_at": "2026-07-13T14:22:02.967948Z", "completed_at": "2026-07-13T14:22:02.967960Z"}], "thread_id": "Thread-2 (worker)", "execution_time": 0.029038190841674805, "adapter_response": {}, "message": null, "failures": null, "unique_id": "model.rebate_transformation_layer.mart_affiliate_summary", "compiled": true, "compiled_code": "with rebates as (\n    select * from DEV_MCP_DB.PUBLIC.int_rebates\n),\n\ndim_partners as (\n    select * from DEV_MCP_DB.PUBLIC.dim_partners\n)\n\nselect\n    dp.affiliate_id,\n    dp.affiliate_name,\n    dp.state,\n    dp.program_tier,\n    dp.partner_name,\n    count(r.unique_key) as total_transactions,\n    count(case when r.is_exception = false then 1 end) as clean_transactions,\n    count(case when r.is_exception = true then 1 end) as exception_count,\n    count(case when r.exception_type = 'zero_amount' then 1 end) as zero_amount_count,\n    count(case when r.exception_type = 'null_partner' then 1 end) as null_partner_count,\n    sum(case when r.is_exception = false then r.net_amount else 0 end) as total_rebate_amount,\n    \n    case \n    when \n        -- Affiliate has transactions\n        count(r.unique_key) > 0\n        -- AND every transaction has either zero, null, or negative amount\n        -- avoid memo/partner issue flags as indicative of being a shop silent\n        and count(case when r.exception_type not in ('zero_amount', 'null_amount', 'negative_amount') \n                       and r.is_exception = false \n                       then 1 end) = 0\n        and count(case when r.exception_type in ('zero_amount', 'null_amount', 'negative_amount') \n                       then 1 end) > 0\n    then true\n    else false\nend as is_silent_shop\n\nfrom dim_partners dp\nleft join rebates r on dp.affiliate_id = r.affiliate_id\ngroup by 1, 2, 3, 4, 5", "relation_name": "DEV_MCP_DB.PUBLIC.mart_affiliate_summary", "batch_results": null}, {"status": "success", "timing": [{"name": "compile", "started_at": "2026-07-13T14:22:02.959792Z", "completed_at": "2026-07-13T14:22:02.968852Z"}, {"name": "execute", "started_at": "2026-07-13T14:22:02.971313Z", "completed_at": "2026-07-13T14:22:02.971324Z"}], "thread_id": "Thread-5 (worker)", "execution_time": 0.030310869216918945, "adapter_response": {}, "message": null, "failures": null, "unique_id": "test.rebate_transformation_layer.not_null_dim_partners_affiliate_id.749c166b39", "compiled": true, "compiled_code": "\n    \n    \n\n\n\nselect affiliate_id\nfrom DEV_MCP_DB.PUBLIC.dim_partners\nwhere affiliate_id is null\n\n\n", "relation_name": null, "batch_results": null}, {"status": "success", "timing": [{"name": "compile", "started_at": "2026-07-13T14:22:02.953557Z", "completed_at": "2026-07-13T14:22:02.969419Z"}, {"name": "execute", "started_at": "2026-07-13T14:22:02.972381Z", "completed_at": "2026-07-13T14:22:02.972393Z"}], "thread_id": "Thread-4 (worker)", "execution_time": 0.030168771743774414, "adapter_response": {}, "message": null, "failures": null, "unique_id": "test.rebate_transformation_layer.unique_dim_partners_affiliate_id.eb9a74e66b", "compiled": true, "compiled_code": "\n    \n    \n\nselect\n    affiliate_id as unique_field,\n    count(*) as n_records\n\nfrom DEV_MCP_DB.PUBLIC.dim_partners\nwhere affiliate_id is not null\ngroup by affiliate_id\nhaving count(*) > 1\n\n\n", "relation_name": null, "batch_results": null}, {"status": "success", "timing": [{"name": "compile", "started_at": "2026-07-13T14:22:02.978191Z", "completed_at": "2026-07-13T14:22:02.990079Z"}, {"name": "execute", "started_at": "2026-07-13T14:22:03.002741Z", "completed_at": "2026-07-13T14:22:03.002761Z"}], "thread_id": "Thread-3 (worker)", "execution_time": 0.029656648635864258, "adapter_response": {}, "message": null, "failures": null, "unique_id": "test.rebate_transformation_layer.not_null_fact_rebate_payouts_affiliate_id.734e144335", "compiled": true, "compiled_code": "\n    \n    \n\n\n\nselect affiliate_id\nfrom DEV_MCP_DB.PUBLIC.fact_rebate_payouts\nwhere affiliate_id is null\n\n\n", "relation_name": null, "batch_results": null}, {"status": "success", "timing": [{"name": "compile", "started_at": "2026-07-13T14:22:02.983441Z", "completed_at": "2026-07-13T14:22:03.003650Z"}, {"name": "execute", "started_at": "2026-07-13T14:22:03.006424Z", "completed_at": "2026-07-13T14:22:03.006436Z"}], "thread_id": "Thread-2 (worker)", "execution_time": 0.03271031379699707, "adapter_response": {}, "message": null, "failures": null, "unique_id": "test.rebate_transformation_layer.not_null_fact_rebate_payouts_rebate_payout_id.2b7b160301", "compiled": true, "compiled_code": "\n    \n    \n\n\n\nselect rebate_payout_id\nfrom DEV_MCP_DB.PUBLIC.fact_rebate_payouts\nwhere rebate_payout_id is null\n\n\n", "relation_name": null, "batch_results": null}, {"status": "success", "timing": [{"name": "compile", "started_at": "2026-07-13T14:22:02.990650Z", "completed_at": "2026-07-13T14:22:03.005243Z"}, {"name": "execute", "started_at": "2026-07-13T14:22:03.007949Z", "completed_at": "2026-07-13T14:22:03.007959Z"}], "thread_id": "Thread-5 (worker)", "execution_time": 0.031121253967285156, "adapter_response": {}, "message": null, "failures": null, "unique_id": "test.rebate_transformation_layer.relationships_fact_rebate_payouts_affiliate_id__affiliate_id__ref_dim_partners_.28f5db59fe", "compiled": true, "compiled_code": "\n    \n    \n\nwith child as (\n    select affiliate_id as from_field\n    from DEV_MCP_DB.PUBLIC.fact_rebate_payouts\n    where affiliate_id is not null\n),\n\nparent as (\n    select affiliate_id as to_field\n    from DEV_MCP_DB.PUBLIC.dim_partners\n)\n\nselect\n    from_field\n\nfrom child\nleft join parent\n    on child.from_field = parent.to_field\n\nwhere parent.to_field is null\n\n\n", "relation_name": null, "batch_results": null}, {"status": "success", "timing": [{"name": "compile", "started_at": "2026-07-13T14:22:02.996731Z", "completed_at": "2026-07-13T14:22:03.005738Z"}, {"name": "execute", "started_at": "2026-07-13T14:22:03.008775Z", "completed_at": "2026-07-13T14:22:03.008788Z"}], "thread_id": "Thread-4 (worker)", "execution_time": 0.031340599060058594, "adapter_response": {}, "message": null, "failures": null, "unique_id": "test.rebate_transformation_layer.unique_fact_rebate_payouts_affiliate_id.86eabd99ed", "compiled": true, "compiled_code": "\n    \n    \n\nselect\n    affiliate_id as unique_field,\n    count(*) as n_records\n\nfrom DEV_MCP_DB.PUBLIC.fact_rebate_payouts\nwhere affiliate_id is not null\ngroup by affiliate_id\nhaving count(*) > 1\n\n\n", "relation_name": null, "batch_results": null}, {"status": "success", "timing": [{"name": "compile", "started_at": "2026-07-13T14:22:03.012877Z", "completed_at": "2026-07-13T14:22:03.021942Z"}, {"name": "execute", "started_at": "2026-07-13T14:22:03.037092Z", "completed_at": "2026-07-13T14:22:03.037110Z"}], "thread_id": "Thread-3 (worker)", "execution_time": 0.02992868423461914, "adapter_response": {}, "message": null, "failures": null, "unique_id": "test.rebate_transformation_layer.unique_fact_rebate_payouts_rebate_payout_id.0b0bc0c74e", "compiled": true, "compiled_code": "\n    \n    \n\nselect\n    rebate_payout_id as unique_field,\n    count(*) as n_records\n\nfrom DEV_MCP_DB.PUBLIC.fact_rebate_payouts\nwhere rebate_payout_id is not null\ngroup by rebate_payout_id\nhaving count(*) > 1\n\n\n", "relation_name": null, "batch_results": null}, {"status": "success", "timing": [{"name": "compile", "started_at": "2026-07-13T14:22:03.022567Z", "completed_at": "2026-07-13T14:22:03.038683Z"}, {"name": "execute", "started_at": "2026-07-13T14:22:03.040499Z", "completed_at": "2026-07-13T14:22:03.040520Z"}], "thread_id": "Thread-2 (worker)", "execution_time": 0.02839064598083496, "adapter_response": {}, "message": null, "failures": null, "unique_id": "test.rebate_transformation_layer.assert_anomaly_regression_baseline", "compiled": true, "compiled_code": "-- =========================================================================\n-- Assert Anomaly Regression Baseline:\n-- \n-- Original production dataset: 106 affiliate locations flagged as silent shops\n-- Synthesized/anonymized dataset: ~75 affiliate locations flagged under the same rule\n-- The difference reflects resampling during data synthesis\n--\n-- This test does NOT assert an exact count because the synthesized dataset\n-- introduces natural variance. Instead it guards against complete detection collapse:\n-- if zero exceptions are flagged, the detection rule itself has broken.\n--\n-- dbt singular tests pass when the query returns zero rows.\n-- This query returns one row only when detection has completely failed.\n-- =========================================================================\n\n\nselect 1\nfrom DEV_MCP_DB.PUBLIC.mart_affiliate_summary\nhaving sum(case when is_silent_shop = true then 1 else 0 end) = 0", "relation_name": null, "batch_results": null}, {"status": "success", "timing": [{"name": "compile", "started_at": "2026-07-13T14:22:03.026498Z", "completed_at": "2026-07-13T14:22:03.039377Z"}, {"name": "execute", "started_at": "2026-07-13T14:22:03.041404Z", "completed_at": "2026-07-13T14:22:03.041414Z"}], "thread_id": "Thread-5 (worker)", "execution_time": 0.022940397262573242, "adapter_response": {}, "message": null, "failures": null, "unique_id": "test.rebate_transformation_layer.not_null_mart_affiliate_summary_affiliate_id.46d0d399f2", "compiled": true, "compiled_code": "\n    \n    \n\n\n\nselect affiliate_id\nfrom DEV_MCP_DB.PUBLIC.mart_affiliate_summary\nwhere affiliate_id is null\n\n\n", "relation_name": null, "batch_results": null}, {"status": "success", "timing": [{"name": "compile", "started_at": "2026-07-13T14:22:03.031847Z", "completed_at": "2026-07-13T14:22:03.039895Z"}, {"name": "execute", "started_at": "2026-07-13T14:22:03.042255Z", "completed_at": "2026-07-13T14:22:03.042266Z"}], "thread_id": "Thread-4 (worker)", "execution_time": 0.023128271102905273, "adapter_response": {}, "message": null, "failures": null, "unique_id": "test.rebate_transformation_layer.unique_mart_affiliate_summary_affiliate_id.56cf1d15f5", "compiled": true, "compiled_code": "\n    \n    \n\nselect\n    affiliate_id as unique_field,\n    count(*) as n_records\n\nfrom DEV_MCP_DB.PUBLIC.mart_affiliate_summary\nwhere affiliate_id is not null\ngroup by affiliate_id\nhaving count(*) > 1\n\n\n", "relation_name": null, "batch_results": null}], "elapsed_time": 2.1692252159118652, "args": {"require_unique_project_resource_names": false, "profiles_dir": ".", "require_resource_names_without_spaces": true, "indirect_selection": "eager", "invocation_command": "dbt docs generate --profiles-dir .", "log_path": "/home/runner/work/rebate-intelligence-pipeline/rebate-intelligence-pipeline/rebate_transformation_layer/logs", "use_colors_file": true, "printer_width": 80, "use_fast_test_edges": false, "log_file_max_bytes": 10485760, "introspect": true, "require_yaml_configuration_for_mf_time_spines": false, "sqlparse": {"MAX_GROUPING_DEPTH": null, "MAX_GROUPING_TOKENS": null}, "send_anonymous_usage_stats": true, "empty_catalog": false, "version_check": true, "require_explicit_package_overrides_for_builtin_materializations": true, "state_modified_compare_vars": false, "which": "generate", "partial_parse_file_diff": true, "select": [], "write_json": true, "log_format": "default", "static": false, "upload_to_artifacts_ingest_api": false, "strict_mode": false, "require_generic_test_arguments_property": true, "populate_cache": true, "warn_error_options": {"error": [], "warn": [], "silence": []}, "macro_debugging": false, "require_nested_cumulative_type_params": false, "log_format_file": "debug", "exclude": [], "favor_state": false, "skip_nodes_if_on_run_start_fails": false, "use_colors": true, "log_level": "info", "log_level_file": "debug", "print": true, "compile": true, "quiet": false, "require_batched_execution_for_custom_microbatch_strategy": false, "static_parser": true, "state_modified_compare_more_unrendered_values": false, "defer": false, "show_all_deprecations": false, "cache_selected_only": false, "validate_macro_args": false, "project_dir": "/home/runner/work/rebate-intelligence-pipeline/rebate-intelligence-pipeline/rebate_transformation_layer", "vars": {}, "require_all_warnings_handled_by_warn_error": false, "show_resource_report": false, "require_ref_searches_node_package_before_root": false, "source_freshness_run_project_hooks": true, "partial_parse": true}}